[{"line":1,"elements":[{"line":3,"name":"","description":"","type":"background","keyword":"Background","steps":[{"name":"def dataGenerator = Java.type('helpers.DataGenerator')","result":{"duration":259100,"status":"passed"},"match":{"location":"karate","arguments":[]},"keyword":"*","line":4,"doc_string":{"content_type":"","value":"00:31:43.406 karate.env system property was: null \n","line":4}},{"name":"url apiURL","result":{"duration":44900,"status":"passed"},"match":{"location":"karate","arguments":[]},"keyword":"Given","line":5}]},{"line":9,"name":"Get user: Existing user","description":"","id":"get-user--existing-user","type":"scenario","keyword":"Scenario","steps":[{"name":"params { id: \"#(existingUser.id)\" }","result":{"duration":232000,"status":"passed"},"match":{"location":"karate","arguments":[]},"comments":["## Note that this test case is dependent on the provided REST API application (AppPerformanceTest-0.1-SNAPSHOT.jar)","## which starts with two existing users by default (pepe@pepe.pe1-0.1 and pepe@pepe.pe1-0.2).","## In a more general environment this test case should be removed\/ignored (keyword @ignore)."],"keyword":"Given","line":13},{"name":"path 'user'","result":{"duration":42600,"status":"passed"},"match":{"location":"karate","arguments":[]},"keyword":"Given","line":14},{"name":"method get","result":{"duration":7287300,"status":"passed"},"match":{"location":"karate","arguments":[]},"keyword":"When","line":15,"doc_string":{"content_type":"","value":"00:31:43.409 request:\n1 > GET http:\/\/127.0.0.1:8900\/user?id=pepe%40pepe.pe1-0.1\n1 > Host: 127.0.0.1:8900\n1 > Connection: Keep-Alive\n1 > User-Agent: Apache-HttpClient\/4.5.13 (Java\/1.8.0_301)\n1 > Accept-Encoding: gzip,deflate\n\n\n00:31:43.414 response time in milliseconds: 4\n1 < 200\n1 < Content-Type: application\/json;charset=UTF-8\n1 < Transfer-Encoding: chunked\n1 < Date: Mon, 20 Sep 2021 22:31:43 GMT\n{\"email\":\"pepe@pepe.pe1\",\"name\":\"pepe\",\"id\":\"pepe@pepe.pe1-0.1\",\"bookings\":[{\"idBooking\":\"MAD-ARN-0.27405979383243206\",\"idUser\":\"pepe@pepe.pe1-0.1\",\"origin\":\"MAD\",\"destination\":\"ARN\",\"date\":\"2021-09-20\"},{\"idBooking\":\"MAD-ARN-0.1895170635505371\",\"idUser\":\"pepe@pepe.pe1-0.1\",\"origin\":\"MAD\",\"destination\":\"ARN\",\"date\":\"2021-09-20\"},{\"idBooking\":\"MAD-ARN-0.9548816216350221\",\"idUser\":\"pepe@pepe.pe1-0.1\",\"origin\":\"MAD\",\"destination\":\"ARN\",\"date\":\"2021-09-20\"},{\"idBooking\":\"MAD-ARN-0.3373390603699905\",\"idUser\":\"pepe@pepe.pe1-0.1\",\"origin\":\"MAD\",\"destination\":\"ARN\",\"date\":\"2021-09-20\"},{\"idBooking\":\"MAD-ARN-0.6704460823319927\",\"idUser\":\"pepe@pepe.pe1-0.1\",\"origin\":\"MAD\",\"destination\":\"ARN\",\"date\":\"2021-09-20\"},{\"idBooking\":\"MAD-ARN-0.5576186440120828\",\"idUser\":\"pepe@pepe.pe1-0.1\",\"origin\":\"MAD\",\"destination\":\"ARN\",\"date\":\"2021-09-20\"},{\"idBooking\":\"MAD-ARN-0.4354195073364314\",\"idUser\":\"pepe@pepe.pe1-0.1\",\"origin\":\"MAD\",\"destination\":\"ARN\",\"date\":\"2021-09-20\"},{\"idBooking\":\"MAD-ARN-0.9844648576381295\",\"idUser\":\"pepe@pepe.pe1-0.1\",\"origin\":\"MAD\",\"destination\":\"ARN\",\"date\":\"2021-09-20\"},{\"idBooking\":\"MAD-ARN-0.573634256327533\",\"idUser\":\"pepe@pepe.pe1-0.1\",\"origin\":\"MAD\",\"destination\":\"ARN\",\"date\":\"2021-09-20\"},{\"idBooking\":\"MAD-ARN-0.8272972073826099\",\"idUser\":\"pepe@pepe.pe1-0.1\",\"origin\":\"MAD\",\"destination\":\"ARN\",\"date\":\"2021-09-21\"},{\"idBooking\":\"MAD-ARN-0.4239320001225576\",\"idUser\":\"pepe@pepe.pe1-0.1\",\"origin\":\"MAD\",\"destination\":\"ARN\",\"date\":\"2021-09-20\"},{\"idBooking\":\"MAD-ARN-0.3900811739297385\",\"idUser\":\"pepe@pepe.pe1-0.1\",\"origin\":\"MAD\",\"destination\":\"ARN\",\"date\":\"2021-09-20\"},{\"idBooking\":\"MAD-ARN-0.9801372671002553\",\"idUser\":\"pepe@pepe.pe1-0.1\",\"origin\":\"MAD\",\"destination\":\"ARN\",\"date\":\"2021-09-20\"},{\"idBooking\":\"MAD-ARN-0.2662863438949502\",\"idUser\":\"pepe@pepe.pe1-0.1\",\"origin\":\"MAD\",\"destination\":\"ARN\",\"date\":\"2021-09-21\"},{\"idBooking\":\"MAD-ARN-0.685999672427051\",\"idUser\":\"pepe@pepe.pe1-0.1\",\"origin\":\"MAD\",\"destination\":\"ARN\",\"date\":\"2021-09-21\"},{\"idBooking\":\"BBB-AAA-0.8473371278448251\",\"idUser\":\"pepe@pepe.pe1-0.1\",\"origin\":\"BBB\",\"destination\":\"AAA\",\"date\":\"2022-01-25\"},{\"idBooking\":\"MAD-ARN-0.6467707763673122\",\"idUser\":\"pepe@pepe.pe1-0.1\",\"origin\":\"MAD\",\"destination\":\"ARN\",\"date\":\"2021-09-21\"},{\"idBooking\":\"AWF-AWC-0.06910200440678205\",\"idUser\":\"pepe@pepe.pe1-0.1\",\"origin\":\"AWF\",\"destination\":\"AWC\",\"date\":\"2021-09-20\"},{\"idBooking\":\"MAD-ARN-0.41257904178293847\",\"idUser\":\"pepe@pepe.pe1-0.1\",\"origin\":\"MAD\",\"destination\":\"ARN\",\"date\":\"2021-09-20\"},{\"idBooking\":\"MAD-ARN-0.9135038080153004\",\"idUser\":\"pepe@pepe.pe1-0.1\",\"origin\":\"MAD\",\"destination\":\"ARN\",\"date\":\"2021-09-20\"},{\"idBooking\":\"MAD-ARN-0.6654574707964476\",\"idUser\":\"pepe@pepe.pe1-0.1\",\"origin\":\"MAD\",\"destination\":\"ARN\",\"date\":\"2021-09-20\"},{\"idBooking\":\"MAD-ARN-0.5534282522945362\",\"idUser\":\"pepe@pepe.pe1-0.1\",\"origin\":\"MAD\",\"destination\":\"ARN\",\"date\":\"2021-09-20\"},{\"idBooking\":\"MAD-ARN-0.6090871631395023\",\"idUser\":\"pepe@pepe.pe1-0.1\",\"origin\":\"MAD\",\"destination\":\"ARN\",\"date\":\"2021-09-20\"},{\"idBooking\":\"MAD-ARN-0.4584180438515649\",\"idUser\":\"pepe@pepe.pe1-0.1\",\"origin\":\"MAD\",\"destination\":\"ARN\",\"date\":\"2021-09-20\"},{\"idBooking\":\"MAD-ARN-0.0766033182470045\",\"idUser\":\"pepe@pepe.pe1-0.1\",\"origin\":\"MAD\",\"destination\":\"ARN\",\"date\":\"2021-09-21\"},{\"idBooking\":\"MAD-ARN-0.7802964635412594\",\"idUser\":\"pepe@pepe.pe1-0.1\",\"origin\":\"MAD\",\"destination\":\"ARN\",\"date\":\"2021-09-21\"},{\"idBooking\":\"MAD-ARN-0.289671696881859\",\"idUser\":\"pepe@pepe.pe1-0.1\",\"origin\":\"MAD\",\"destination\":\"ARN\",\"date\":\"2021-09-21\"},{\"idBooking\":\"MAD-ARN-0.22047933158640243\",\"idUser\":\"pepe@pepe.pe1-0.1\",\"origin\":\"MAD\",\"destination\":\"ARN\",\"date\":\"2021-09-20\"},{\"idBooking\":\"MAD-ARN-0.4836245564209497\",\"idUser\":\"pepe@pepe.pe1-0.1\",\"origin\":\"MAD\",\"destination\":\"ARN\",\"date\":\"2021-09-20\"},{\"idBooking\":\"MAD-ARN-0.759725606866861\",\"idUser\":\"pepe@pepe.pe1-0.1\",\"origin\":\"MAD\",\"destination\":\"ARN\",\"date\":\"2021-09-20\"},{\"idBooking\":\"MAD-ARN-0.5014806461333827\",\"idUser\":\"pepe@pepe.pe1-0.1\",\"origin\":\"MAD\",\"destination\":\"ARN\",\"date\":\"2021-09-20\"},{\"idBooking\":\"MAD-ARN-0.3476970898021826\",\"idUser\":\"pepe@pepe.pe1-0.1\",\"origin\":\"MAD\",\"destination\":\"ARN\",\"date\":\"2021-09-20\"},{\"idBooking\":\"MAD-ARN-0.7933644282153766\",\"idUser\":\"pepe@pepe.pe1-0.1\",\"origin\":\"MAD\",\"destination\":\"ARN\",\"date\":\"2021-09-20\"},{\"idBooking\":\"MAD-ARN-0.6838889588738892\",\"idUser\":\"pepe@pepe.pe1-0.1\",\"origin\":\"MAD\",\"destination\":\"ARN\",\"date\":\"2021-09-21\"}]}\n","line":15}},{"name":"status 200","result":{"duration":3500,"status":"passed"},"match":{"location":"karate","arguments":[]},"keyword":"Then","line":16},{"name":"match response == { email: \"#(existingUser.email)\", name: \"#(existingUser.name)\", id: \"#(existingUser.id)\", bookings: \"#array\" }","result":{"duration":3201500,"status":"passed"},"match":{"location":"karate","arguments":[]},"keyword":"And","line":17}],"tags":[{"name":"@GetUser","line":8}]},{"line":3,"name":"","description":"","type":"background","keyword":"Background","steps":[{"name":"def dataGenerator = Java.type('helpers.DataGenerator')","result":{"duration":264500,"status":"passed"},"match":{"location":"karate","arguments":[]},"keyword":"*","line":4,"doc_string":{"content_type":"","value":"00:31:43.406 karate.env system property was: null \n","line":4}},{"name":"url apiURL","result":{"duration":56100,"status":"passed"},"match":{"location":"karate","arguments":[]},"keyword":"Given","line":5}]},{"line":20,"name":"Get all users","description":"","id":"get-all-users","type":"scenario","keyword":"Scenario","steps":[{"name":"path 'user\/all'","result":{"duration":637900,"status":"passed"},"match":{"location":"karate","arguments":[]},"keyword":"Given","line":21},{"name":"method get","result":{"duration":16435200,"status":"passed"},"match":{"location":"karate","arguments":[]},"keyword":"When","line":22,"doc_string":{"content_type":"","value":"00:31:43.409 request:\n1 > GET http:\/\/127.0.0.1:8900\/user\/all\n1 > Host: 127.0.0.1:8900\n1 > Connection: Keep-Alive\n1 > User-Agent: Apache-HttpClient\/4.5.13 (Java\/1.8.0_301)\n1 > Accept-Encoding: gzip,deflate\n\n\n00:31:43.422 response time in milliseconds: 11\n1 < 200\n1 < Content-Type: application\/json;charset=UTF-8\n1 < Transfer-Encoding: chunked\n1 < Date: Mon, 20 Sep 2021 22:31:43 GMT\n[{\"email\":\"pepe@pepe.pe1\",\"name\":\"pepe\",\"id\":\"pepe@pepe.pe1-0.1\",\"bookings\":[{\"idBooking\":\"MAD-ARN-0.759725606866861\",\"idUser\":\"pepe@pepe.pe1-0.1\",\"origin\":\"MAD\",\"destination\":\"ARN\",\"date\":\"2021-09-20\"},{\"idBooking\":\"MAD-ARN-0.573634256327533\",\"idUser\":\"pepe@pepe.pe1-0.1\",\"origin\":\"MAD\",\"destination\":\"ARN\",\"date\":\"2021-09-20\"},{\"idBooking\":\"MAD-ARN-0.685999672427051\",\"idUser\":\"pepe@pepe.pe1-0.1\",\"origin\":\"MAD\",\"destination\":\"ARN\",\"date\":\"2021-09-21\"},{\"idBooking\":\"MAD-ARN-0.3373390603699905\",\"idUser\":\"pepe@pepe.pe1-0.1\",\"origin\":\"MAD\",\"destination\":\"ARN\",\"date\":\"2021-09-20\"},{\"idBooking\":\"MAD-ARN-0.4239320001225576\",\"idUser\":\"pepe@pepe.pe1-0.1\",\"origin\":\"MAD\",\"destination\":\"ARN\",\"date\":\"2021-09-20\"},{\"idBooking\":\"AWF-AWC-0.06910200440678205\",\"idUser\":\"pepe@pepe.pe1-0.1\",\"origin\":\"AWF\",\"destination\":\"AWC\",\"date\":\"2021-09-20\"},{\"idBooking\":\"MAD-ARN-0.8272972073826099\",\"idUser\":\"pepe@pepe.pe1-0.1\",\"origin\":\"MAD\",\"destination\":\"ARN\",\"date\":\"2021-09-21\"},{\"idBooking\":\"MAD-ARN-0.22047933158640243\",\"idUser\":\"pepe@pepe.pe1-0.1\",\"origin\":\"MAD\",\"destination\":\"ARN\",\"date\":\"2021-09-20\"},{\"idBooking\":\"BBB-AAA-0.8473371278448251\",\"idUser\":\"pepe@pepe.pe1-0.1\",\"origin\":\"BBB\",\"destination\":\"AAA\",\"date\":\"2022-01-25\"},{\"idBooking\":\"MAD-ARN-0.6838889588738892\",\"idUser\":\"pepe@pepe.pe1-0.1\",\"origin\":\"MAD\",\"destination\":\"ARN\",\"date\":\"2021-09-21\"},{\"idBooking\":\"MAD-ARN-0.9135038080153004\",\"idUser\":\"pepe@pepe.pe1-0.1\",\"origin\":\"MAD\",\"destination\":\"ARN\",\"date\":\"2021-09-20\"},{\"idBooking\":\"MAD-ARN-0.289671696881859\",\"idUser\":\"pepe@pepe.pe1-0.1\",\"origin\":\"MAD\",\"destination\":\"ARN\",\"date\":\"2021-09-21\"},{\"idBooking\":\"MAD-ARN-0.4836245564209497\",\"idUser\":\"pepe@pepe.pe1-0.1\",\"origin\":\"MAD\",\"destination\":\"ARN\",\"date\":\"2021-09-20\"},{\"idBooking\":\"MAD-ARN-0.3900811739297385\",\"idUser\":\"pepe@pepe.pe1-0.1\",\"origin\":\"MAD\",\"destination\":\"ARN\",\"date\":\"2021-09-20\"},{\"idBooking\":\"MAD-ARN-0.5534282522945362\",\"idUser\":\"pepe@pepe.pe1-0.1\",\"origin\":\"MAD\",\"destination\":\"ARN\",\"date\":\"2021-09-20\"},{\"idBooking\":\"MAD-ARN-0.6654574707964476\",\"idUser\":\"pepe@pepe.pe1-0.1\",\"origin\":\"MAD\",\"destination\":\"ARN\",\"date\":\"2021-09-20\"},{\"idBooking\":\"MAD-ARN-0.6704460823319927\",\"idUser\":\"pepe@pepe.pe1-0.1\",\"origin\":\"MAD\",\"destination\":\"ARN\",\"date\":\"2021-09-20\"},{\"idBooking\":\"MAD-ARN-0.27405979383243206\",\"idUser\":\"pepe@pepe.pe1-0.1\",\"origin\":\"MAD\",\"destination\":\"ARN\",\"date\":\"2021-09-20\"},{\"idBooking\":\"MAD-ARN-0.1895170635505371\",\"idUser\":\"pepe@pepe.pe1-0.1\",\"origin\":\"MAD\",\"destination\":\"ARN\",\"date\":\"2021-09-20\"},{\"idBooking\":\"MAD-ARN-0.4584180438515649\",\"idUser\":\"pepe@pepe.pe1-0.1\",\"origin\":\"MAD\",\"destination\":\"ARN\",\"date\":\"2021-09-20\"},{\"idBooking\":\"MAD-ARN-0.3476970898021826\",\"idUser\":\"pepe@pepe.pe1-0.1\",\"origin\":\"MAD\",\"destination\":\"ARN\",\"date\":\"2021-09-20\"},{\"idBooking\":\"MAD-ARN-0.9801372671002553\",\"idUser\":\"pepe@pepe.pe1-0.1\",\"origin\":\"MAD\",\"destination\":\"ARN\",\"date\":\"2021-09-20\"},{\"idBooking\":\"MAD-ARN-0.6467707763673122\",\"idUser\":\"pepe@pepe.pe1-0.1\",\"origin\":\"MAD\",\"destination\":\"ARN\",\"date\":\"2021-09-21\"},{\"idBooking\":\"MAD-ARN-0.0766033182470045\",\"idUser\":\"pepe@pepe.pe1-0.1\",\"origin\":\"MAD\",\"destination\":\"ARN\",\"date\":\"2021-09-21\"},{\"idBooking\":\"MAD-ARN-0.5576186440120828\",\"idUser\":\"pepe@pepe.pe1-0.1\",\"origin\":\"MAD\",\"destination\":\"ARN\",\"date\":\"2021-09-20\"},{\"idBooking\":\"MAD-ARN-0.5014806461333827\",\"idUser\":\"pepe@pepe.pe1-0.1\",\"origin\":\"MAD\",\"destination\":\"ARN\",\"date\":\"2021-09-20\"},{\"idBooking\":\"MAD-ARN-0.6090871631395023\",\"idUser\":\"pepe@pepe.pe1-0.1\",\"origin\":\"MAD\",\"destination\":\"ARN\",\"date\":\"2021-09-20\"},{\"idBooking\":\"MAD-ARN-0.9844648576381295\",\"idUser\":\"pepe@pepe.pe1-0.1\",\"origin\":\"MAD\",\"destination\":\"ARN\",\"date\":\"2021-09-20\"},{\"idBooking\":\"MAD-ARN-0.41257904178293847\",\"idUser\":\"pepe@pepe.pe1-0.1\",\"origin\":\"MAD\",\"destination\":\"ARN\",\"date\":\"2021-09-20\"},{\"idBooking\":\"MAD-ARN-0.9548816216350221\",\"idUser\":\"pepe@pepe.pe1-0.1\",\"origin\":\"MAD\",\"destination\":\"ARN\",\"date\":\"2021-09-20\"},{\"idBooking\":\"MAD-ARN-0.7802964635412594\",\"idUser\":\"pepe@pepe.pe1-0.1\",\"origin\":\"MAD\",\"destination\":\"ARN\",\"date\":\"2021-09-21\"},{\"idBooking\":\"MAD-ARN-0.7933644282153766\",\"idUser\":\"pepe@pepe.pe1-0.1\",\"origin\":\"MAD\",\"destination\":\"ARN\",\"date\":\"2021-09-20\"},{\"idBooking\":\"MAD-ARN-0.2662863438949502\",\"idUser\":\"pepe@pepe.pe1-0.1\",\"origin\":\"MAD\",\"destination\":\"ARN\",\"date\":\"2021-09-21\"},{\"idBooking\":\"MAD-ARN-0.4354195073364314\",\"idUser\":\"pepe@pepe.pe1-0.1\",\"origin\":\"MAD\",\"destination\":\"ARN\",\"date\":\"2021-09-20\"}]},{\"email\":\"pepe@pepe.pe2\",\"name\":\"pepe\",\"id\":\"pepe@pepe.pe1-0.2\",\"bookings\":[]},{\"email\":\"Karl@email.com\",\"name\":\"Karl\",\"id\":\"Karl@email.com-0.4248604193037997\",\"bookings\":[]},{\"email\":\"asdfasdf@asdf.com\",\"name\":\"Karl\",\"id\":\"asdfasdf@asdf.com-0.9143639277534428\",\"bookings\":[]},{\"email\":\"asdfasdf@asdfcom\",\"name\":\"Karl\",\"id\":\"asdfasdf@asdfcom-0.5240411151230305\",\"bookings\":[]},{\"email\":\"asd@as.com\",\"name\":\"@£\u20AC$dsf£$@\u20AC@\u20AC{ä\",\"id\":\"asd@as.com-0.9515793715119747\",\"bookings\":[]},{\"email\":\"as@£@\u20AC@d@$\u20AC[\u20AC{as.com\",\"name\":\"@£\u20AC$dsf£$@\u20AC@\u20AC{ä\",\"id\":\"as@£@\u20AC@d@$\u20AC[\u20AC{as.com-0.41242310136527605\",\"bookings\":[]},{\"email\":\"gerri537@email.com\",\"name\":\"Alfred Mayer\",\"id\":\"gerri537@email.com-0.9153014151290396\",\"bookings\":[{\"idBooking\":\"MAD-ARN-0.08687511124244895\",\"idUser\":\"gerri537@email.com-0.9153014151290396\",\"origin\":\"MAD\",\"destination\":\"ARN\",\"date\":\"2021-09-20\"}]},{\"email\":\"kera153@email.com\",\"name\":\"Hilario Pfannerstill\",\"id\":\"kera153@email.com-0.30680021454383055\",\"bookings\":[]},{\"email\":\"eusebio712@email.com\",\"name\":\"Ms. Chia Lynch\",\"id\":\"eusebio712@email.com-0.45949619545467824\",\"bookings\":[{\"idBooking\":\"MAD-ARN-0.7796482727267625\",\"idUser\":\"eusebio712@email.com-0.45949619545467824\",\"origin\":\"MAD\",\"destination\":\"ARN\",\"date\":\"2021-09-20\"}]},{\"email\":\"philip839@email.com\",\"name\":\"Johnette Wehner\",\"id\":\"philip839@email.com-0.7393352831869302\",\"bookings\":[]},{\"email\":\"vesta84@email.com\",\"name\":\"Jewell Kuhic\",\"id\":\"vesta84@email.com-0.005754387475619294\",\"bookings\":[{\"idBooking\":\"MAD-ARN-0.428354226140257\",\"idUser\":\"vesta84@email.com-0.005754387475619294\",\"origin\":\"MAD\",\"destination\":\"ARN\",\"date\":\"2021-09-20\"}]},{\"email\":\"erick251@email.com\",\"name\":\"Celestine Predovic\",\"id\":\"erick251@email.com-0.6968013593741477\",\"bookings\":[]},{\"email\":\"ivory122@email.com\",\"name\":\"Miss Walton White\",\"id\":\"ivory122@email.com-0.9294840752457313\",\"bookings\":[{\"idBooking\":\"MAD-ARN-0.8915796110195673\",\"idUser\":\"ivory122@email.com-0.9294840752457313\",\"origin\":\"MAD\",\"destination\":\"ARN\",\"date\":\"2021-09-20\"}]},{\"email\":\"alphonse429@email.com\",\"name\":\"Mrs. Kandice Douglas\",\"id\":\"alphonse429@email.com-0.10097039235098204\",\"bookings\":[{\"idBooking\":\"MAD-ARN-0.733327849406249\",\"idUser\":\"alphonse429@email.com-0.10097039235098204\",\"origin\":\"MAD\",\"destination\":\"ARN\",\"date\":\"2021-09-20\"}]},{\"email\":\"michel856@email.com\",\"name\":\"Benita Fadel\",\"id\":\"michel856@email.com-0.681446490234754\",\"bookings\":[{\"idBooking\":\"MAD-ARN-0.7320177506364\",\"idUser\":\"michel856@email.com-0.681446490234754\",\"origin\":\"MAD\",\"destination\":\"ARN\",\"date\":\"2021-09-20\"}]},{\"email\":\"myron136@email.com\",\"name\":\"Karyn Zulauf\",\"id\":\"myron136@email.com-0.642880975990545\",\"bookings\":[{\"idBooking\":\"MAD-ARN-0.2376538769198443\",\"idUser\":\"myron136@email.com-0.642880975990545\",\"origin\":\"MAD\",\"destination\":\"ARN\",\"date\":\"2021-09-20\"}]},{\"email\":\"salley531@email.com\",\"name\":\"Mr. Fern Brakus\",\"id\":\"salley531@email.com-0.6480649783039201\",\"bookings\":[]},{\"email\":\"spencer15@email.com\",\"name\":\"Bob Mills\",\"id\":\"spencer15@email.com-0.5327407093779907\",\"bookings\":[{\"idBooking\":\"MAD-ARN-0.007217708024605529\",\"idUser\":\"spencer15@email.com-0.5327407093779907\",\"origin\":\"MAD\",\"destination\":\"ARN\",\"date\":\"2021-09-20\"}]},{\"email\":\"nancie365@email.com\",\"name\":\"Tony Stokes\",\"id\":\"nancie365@email.com-0.5379761342207814\",\"bookings\":[]},{\"email\":\"marcelo620@email.com\",\"name\":\"Roma Botsford\",\"id\":\"marcelo620@email.com-0.16574355223440262\",\"bookings\":[{\"idBooking\":\"MAD-ARN-0.03995756937795114\",\"idUser\":\"marcelo620@email.com-0.16574355223440262\",\"origin\":\"MAD\",\"destination\":\"ARN\",\"date\":\"2021-09-20\"}]},{\"email\":\"ashly217@email.com\",\"name\":\"Letty Harris MD\",\"id\":\"ashly217@email.com-0.06393328680556098\",\"bookings\":[]},{\"email\":\"carola488@email.com\",\"name\":\"Lynna Nienow\",\"id\":\"carola488@email.com-0.05799349071783111\",\"bookings\":[{\"idBooking\":\"MAD-ARN-0.03506837488164283\",\"idUser\":\"carola488@email.com-0.05799349071783111\",\"origin\":\"MAD\",\"destination\":\"ARN\",\"date\":\"2021-09-20\"}]},{\"email\":\"leida92@email.com\",\"name\":\"Mr. Jackelyn Swift\",\"id\":\"leida92@email.com-0.02029413994319096\",\"bookings\":[]},{\"email\":\"calvin752@email.com\",\"name\":\"Geoffrey Shields\",\"id\":\"calvin752@email.com-0.9731614044156817\",\"bookings\":[{\"idBooking\":\"MAD-ARN-0.47910541526054484\",\"idUser\":\"calvin752@email.com-0.9731614044156817\",\"origin\":\"MAD\",\"destination\":\"ARN\",\"date\":\"2021-09-20\"}]},{\"email\":\"marg415@email.com\",\"name\":\"Zack Hoeger\",\"id\":\"marg415@email.com-0.6375638895483631\",\"bookings\":[]},{\"email\":\"hilton812@email.com\",\"name\":\"Lori Stehr V\",\"id\":\"hilton812@email.com-0.8235105959803573\",\"bookings\":[{\"idBooking\":\"MAD-ARN-0.28745795478217895\",\"idUser\":\"hilton812@email.com-0.8235105959803573\",\"origin\":\"MAD\",\"destination\":\"ARN\",\"date\":\"2021-09-20\"}]},{\"email\":\"glynis225@email.com\",\"name\":\"Carol McLaughlin\",\"id\":\"glynis225@email.com-0.9743106184339524\",\"bookings\":[]},{\"email\":\"eldridge365@email.com\",\"name\":\"Joannie Rath\",\"id\":\"eldridge365@email.com-0.29643330504195875\",\"bookings\":[{\"idBooking\":\"MAD-ARN-0.8665221217788562\",\"idUser\":\"eldridge365@email.com-0.29643330504195875\",\"origin\":\"MAD\",\"destination\":\"ARN\",\"date\":\"2021-09-20\"}]},{\"email\":\"tory202@email.com\",\"name\":\"Rolando Kohler\",\"id\":\"tory202@email.com-0.753226140075354\",\"bookings\":[]},{\"email\":\"jesus323@email.com\",\"name\":\"Joana Powlowski\",\"id\":\"jesus323@email.com-0.4252677508874787\",\"bookings\":[{\"idBooking\":\"MAD-ARN-0.5098535888023243\",\"idUser\":\"jesus323@email.com-0.4252677508874787\",\"origin\":\"MAD\",\"destination\":\"ARN\",\"date\":\"2021-09-20\"}]},{\"email\":\"ty801@email.com\",\"name\":\"Johnny Nader I\",\"id\":\"ty801@email.com-0.42603245599679196\",\"bookings\":[]},{\"email\":\"dewitt63@email.com\",\"name\":\"Carmelita Bergnaum\",\"id\":\"dewitt63@email.com-0.4787622826424279\",\"bookings\":[{\"idBooking\":\"MAD-ARN-0.8274064934541713\",\"idUser\":\"dewitt63@email.com-0.4787622826424279\",\"origin\":\"MAD\",\"destination\":\"ARN\",\"date\":\"2021-09-20\"}]},{\"email\":\"anibal668@email.com\",\"name\":\"Max Harber\",\"id\":\"anibal668@email.com-0.5326917899344321\",\"bookings\":[]},{\"email\":\"june404@email.com\",\"name\":\"Eusebio Ratke\",\"id\":\"june404@email.com-0.737627616478946\",\"bookings\":[{\"idBooking\":\"MAD-ARN-0.07584307133733326\",\"idUser\":\"june404@email.com-0.737627616478946\",\"origin\":\"MAD\",\"destination\":\"ARN\",\"date\":\"2021-09-20\"}]},{\"email\":\"parker782@email.com\",\"name\":\"Harlan Olson\",\"id\":\"parker782@email.com-0.6312025201286481\",\"bookings\":[]},{\"email\":\"catina581@email.com\",\"name\":\"Natividad Littel\",\"id\":\"catina581@email.com-0.01690939278443082\",\"bookings\":[{\"idBooking\":\"MAD-ARN-0.08745490404659706\",\"idUser\":\"catina581@email.com-0.01690939278443082\",\"origin\":\"MAD\",\"destination\":\"ARN\",\"date\":\"2021-09-20\"}]},{\"email\":\"kate719@email.com\",\"name\":\"Miss Tish Turner\",\"id\":\"kate719@email.com-0.5732415789229085\",\"bookings\":[]},{\"email\":\"ulysses231@email.com\",\"name\":\"Clementina O'Keefe\",\"id\":\"ulysses231@email.com-0.7705945649984989\",\"bookings\":[{\"idBooking\":\"MAD-ARN-0.12925753266762086\",\"idUser\":\"ulysses231@email.com-0.7705945649984989\",\"origin\":\"MAD\",\"destination\":\"ARN\",\"date\":\"2021-09-20\"}]},{\"email\":\"assunta170@email.com\",\"name\":\"Caron Ullrich\",\"id\":\"assunta170@email.com-0.7219790642694035\",\"bookings\":[]},{\"email\":\"herlinda566@email.com\",\"name\":\"Rosaline Schroeder II\",\"id\":\"herlinda566@email.com-0.17830979677534553\",\"bookings\":[{\"idBooking\":\"MAD-ARN-0.3282636329750245\",\"idUser\":\"herlinda566@email.com-0.17830979677534553\",\"origin\":\"MAD\",\"destination\":\"ARN\",\"date\":\"2021-09-20\"}]},{\"email\":\"chi388@email.com\",\"name\":\"Mrs. Enda Nitzsche\",\"id\":\"chi388@email.com-0.47301670829079634\",\"bookings\":[]},{\"email\":\"amparo85@email.com\",\"name\":\"Sean Smith II\",\"id\":\"amparo85@email.com-0.5452063123691749\",\"bookings\":[{\"idBooking\":\"MAD-ARN-0.1051688790365346\",\"idUser\":\"amparo85@email.com-0.5452063123691749\",\"origin\":\"MAD\",\"destination\":\"ARN\",\"date\":\"2021-09-20\"}]},{\"email\":\"carrie790@email.com\",\"name\":\"Mrs. Dewey Schulist\",\"id\":\"carrie790@email.com-0.725785659752089\",\"bookings\":[]},{\"email\":\"lindsay935@email.com\",\"name\":\"Davis Howell\",\"id\":\"lindsay935@email.com-0.43928314345786246\",\"bookings\":[{\"idBooking\":\"MAD-ARN-0.2040469646746489\",\"idUser\":\"lindsay935@email.com-0.43928314345786246\",\"origin\":\"MAD\",\"destination\":\"ARN\",\"date\":\"2021-09-20\"}]},{\"email\":\"marnie814@email.com\",\"name\":\"Pinkie Daniel\",\"id\":\"marnie814@email.com-0.09519718611657835\",\"bookings\":[]},{\"email\":\"ernestine759@email.com\",\"name\":\"Melony Little\",\"id\":\"ernestine759@email.com-0.09957628452135969\",\"bookings\":[{\"idBooking\":\"MAD-ARN-0.26284442251973117\",\"idUser\":\"ernestine759@email.com-0.09957628452135969\",\"origin\":\"MAD\",\"destination\":\"ARN\",\"date\":\"2021-09-21\"}]},{\"email\":\"lonnie261@email.com\",\"name\":\"Steve Kautzer III\",\"id\":\"lonnie261@email.com-0.2257557205063464\",\"bookings\":[]},{\"email\":\"everette342@email.com\",\"name\":\"Venus Konopelski\",\"id\":\"everette342@email.com-0.5370476921265052\",\"bookings\":[{\"idBooking\":\"MAD-ARN-0.5873185360183675\",\"idUser\":\"everette342@email.com-0.5370476921265052\",\"origin\":\"MAD\",\"destination\":\"ARN\",\"date\":\"2021-09-21\"}]},{\"email\":\"santana707@email.com\",\"name\":\"Loida Bergnaum\",\"id\":\"santana707@email.com-0.3388691386870418\",\"bookings\":[]},{\"email\":\"lorenzo625@email.com\",\"name\":\"Mr. Rickey Wiegand\",\"id\":\"lorenzo625@email.com-0.5331825959585768\",\"bookings\":[{\"idBooking\":\"MAD-ARN-0.250647163420909\",\"idUser\":\"lorenzo625@email.com-0.5331825959585768\",\"origin\":\"MAD\",\"destination\":\"ARN\",\"date\":\"2021-09-21\"}]},{\"email\":\"desmond571@email.com\",\"name\":\"Billie Dooley\",\"id\":\"desmond571@email.com-0.05548948878743798\",\"bookings\":[]},{\"email\":\"berry167@email.com\",\"name\":\"Erin Kuhic\",\"id\":\"berry167@email.com-0.8622190815825025\",\"bookings\":[{\"idBooking\":\"MAD-ARN-0.16218164812464564\",\"idUser\":\"berry167@email.com-0.8622190815825025\",\"origin\":\"MAD\",\"destination\":\"ARN\",\"date\":\"2021-09-21\"}]},{\"email\":\"genevive849@email.com\",\"name\":\"Miss Frederick Bergnaum\",\"id\":\"genevive849@email.com-0.33950553008480555\",\"bookings\":[]},{\"email\":\"jere20@email.com\",\"name\":\"Miss Devin Flatley\",\"id\":\"jere20@email.com-0.06033635437463425\",\"bookings\":[{\"idBooking\":\"MAD-ARN-0.8639870954711811\",\"idUser\":\"jere20@email.com-0.06033635437463425\",\"origin\":\"MAD\",\"destination\":\"ARN\",\"date\":\"2021-09-21\"}]},{\"email\":\"lewis693@email.com\",\"name\":\"Ozzie Marks\",\"id\":\"lewis693@email.com-0.7876068350970546\",\"bookings\":[]},{\"email\":\"mirna826@email.com\",\"name\":\"Ligia Gerlach\",\"id\":\"mirna826@email.com-0.9555887396666196\",\"bookings\":[{\"idBooking\":\"MAD-ARN-0.8252949697484783\",\"idUser\":\"mirna826@email.com-0.9555887396666196\",\"origin\":\"MAD\",\"destination\":\"ARN\",\"date\":\"2021-09-21\"}]},{\"email\":\"serena810@email.com\",\"name\":\"Twila Smitham\",\"id\":\"serena810@email.com-0.12608564070582617\",\"bookings\":[{\"idBooking\":\"MAD-ARN-0.9486552915624573\",\"idUser\":\"serena810@email.com-0.12608564070582617\",\"origin\":\"MAD\",\"destination\":\"ARN\",\"date\":\"2021-09-21\"}]},{\"email\":\"hunter43@email.com\",\"name\":\"Franklin Olson\",\"id\":\"hunter43@email.com-0.32347133049979526\",\"bookings\":[{\"idBooking\":\"MAD-ARN-0.40582585655617487\",\"idUser\":\"hunter43@email.com-0.32347133049979526\",\"origin\":\"MAD\",\"destination\":\"ARN\",\"date\":\"2021-09-21\"}]}]\n","line":22}},{"name":"status 200","result":{"duration":2600,"status":"passed"},"match":{"location":"karate","arguments":[]},"keyword":"Then","line":23},{"name":"match response == \"#array\"","result":{"duration":196500,"status":"passed"},"match":{"location":"karate","arguments":[]},"keyword":"And","line":24},{"name":"match each response == { email: \"#string\", name: \"#string\", id: \"#string\", bookings: \"#array\" }","result":{"duration":7646000,"status":"passed"},"match":{"location":"karate","arguments":[]},"comments":["## Validate schema for each user and their bookings.","##","## Note: In a real world test, assuming a sufficiently large user database,","## one may want to skip these schema validations when fetching the whole user database","## as it would be time consuming and superfluous to validate the user database","## each time you run the API tests (we're doing API tests, not database tests).","## It would probably be sufficient to validate the schema for post\/get user and booking."],"keyword":"And","line":33},{"name":"def timeValidator = read('classpath:helpers\/timeValidator.js')","result":{"duration":1010600,"status":"passed"},"match":{"location":"karate","arguments":[]},"keyword":"*","line":34},{"name":"match each response..bookings[*] ==","result":{"duration":48670500,"status":"passed"},"match":{"location":"karate","arguments":[]},"keyword":"And","line":35,"doc_string":{"content_type":"","value":"{\n  idBooking: \"#string\",\n  idUser: \"#string\",\n  origin: \"#string\",\n  destination: \"#string\",\n  date: \"#? timeValidator(_)\"\n}","line":35}}],"tags":[{"name":"@GetAllUsers","line":19}]},{"line":3,"name":"","description":"","type":"background","keyword":"Background","steps":[{"name":"def dataGenerator = Java.type('helpers.DataGenerator')","result":{"duration":285600,"status":"passed"},"match":{"location":"karate","arguments":[]},"keyword":"*","line":4,"doc_string":{"content_type":"","value":"00:31:43.411 karate.env system property was: null \n","line":4}},{"name":"url apiURL","result":{"duration":64100,"status":"passed"},"match":{"location":"karate","arguments":[]},"keyword":"Given","line":5}]},{"line":47,"name":"Create a user","description":"","id":"create-a-user","type":"scenario","keyword":"Scenario","steps":[{"name":"def user =","result":{"duration":34471900,"status":"passed"},"match":{"location":"karate","arguments":[]},"keyword":"*","line":48,"doc_string":{"content_type":"","value":"{\n  email: #(dataGenerator.getRandomEmail()),\n  name: #(dataGenerator.getRandomName())        \n}","line":48}},{"name":"path 'user'","result":{"duration":320400,"status":"passed"},"match":{"location":"karate","arguments":[]},"comments":["## Create user"],"keyword":"Given","line":56},{"name":"request user","result":{"duration":115300,"status":"passed"},"match":{"location":"karate","arguments":[]},"keyword":"And","line":57},{"name":"method Post","result":{"duration":5957200,"status":"passed"},"match":{"location":"karate","arguments":[]},"keyword":"When","line":58,"doc_string":{"content_type":"","value":"00:31:43.449 request:\n1 > POST http:\/\/127.0.0.1:8900\/user\n1 > Content-Type: application\/json; charset=UTF-8\n1 > Content-Length: 58\n1 > Host: 127.0.0.1:8900\n1 > Connection: Keep-Alive\n1 > User-Agent: Apache-HttpClient\/4.5.13 (Java\/1.8.0_301)\n1 > Accept-Encoding: gzip,deflate\n{\"email\":\"estela21@email.com\",\"name\":\"Miss Roseanne Ryan\"}\n\n00:31:43.453 response time in milliseconds: 4\n1 < 201\n1 < Content-Type: application\/json;charset=UTF-8\n1 < Transfer-Encoding: chunked\n1 < Date: Mon, 20 Sep 2021 22:31:43 GMT\n{\"email\":\"estela21@email.com\",\"name\":\"Miss Roseanne Ryan\",\"id\":\"estela21@email.com-0.34966031856868396\",\"bookings\":[]}\n","line":58}},{"name":"status 201","result":{"duration":3800,"status":"passed"},"match":{"location":"karate","arguments":[]},"keyword":"Then","line":59},{"name":"match response == { email: #(user.email), name: #(user.name), id: \"#string\", bookings: \"#array\" }","result":{"duration":952700,"status":"passed"},"match":{"location":"karate","arguments":[]},"keyword":"And","line":60},{"name":"def userId = response.id","result":{"duration":2010500,"status":"passed"},"match":{"location":"karate","arguments":[]},"keyword":"*","line":62},{"name":"params { id: #(userId) }","result":{"duration":710300,"status":"passed"},"match":{"location":"karate","arguments":[]},"comments":["## Get user and check that it was successfully created"],"keyword":"Given","line":65},{"name":"path 'user'","result":{"duration":60900,"status":"passed"},"match":{"location":"karate","arguments":[]},"keyword":"Given","line":66},{"name":"method get","result":{"duration":5219900,"status":"passed"},"match":{"location":"karate","arguments":[]},"keyword":"When","line":67,"doc_string":{"content_type":"","value":"00:31:43.459 request:\n2 > GET http:\/\/127.0.0.1:8900\/user?id=estela21%40email.com-0.34966031856868396\n2 > Host: 127.0.0.1:8900\n2 > Connection: Keep-Alive\n2 > User-Agent: Apache-HttpClient\/4.5.13 (Java\/1.8.0_301)\n2 > Accept-Encoding: gzip,deflate\n\n\n00:31:43.462 response time in milliseconds: 3\n2 < 200\n2 < Content-Type: application\/json;charset=UTF-8\n2 < Transfer-Encoding: chunked\n2 < Date: Mon, 20 Sep 2021 22:31:43 GMT\n{\"email\":\"estela21@email.com\",\"name\":\"Miss Roseanne Ryan\",\"id\":\"estela21@email.com-0.34966031856868396\",\"bookings\":[]}\n","line":67}},{"name":"status 200","result":{"duration":4300,"status":"passed"},"match":{"location":"karate","arguments":[]},"keyword":"Then","line":68},{"name":"match response == { email: \"#string\", name: \"#string\", id: \"#string\", bookings: \"#array\" }","result":{"duration":568800,"status":"passed"},"match":{"location":"karate","arguments":[]},"keyword":"And","line":69},{"name":"match response contains user","result":{"duration":90400,"status":"passed"},"match":{"location":"karate","arguments":[]},"keyword":"And","line":70}],"tags":[{"name":"@CreateUser","line":46}]},{"line":3,"name":"","description":"","type":"background","keyword":"Background","steps":[{"name":"def dataGenerator = Java.type('helpers.DataGenerator')","result":{"duration":243000,"status":"passed"},"match":{"location":"karate","arguments":[]},"keyword":"*","line":4,"doc_string":{"content_type":"","value":"00:31:43.413 karate.env system property was: null \n","line":4}},{"name":"url apiURL","result":{"duration":47900,"status":"passed"},"match":{"location":"karate","arguments":[]},"keyword":"Given","line":5}]},{"line":83,"name":"Get User: \"Indorrect user id\"","description":"","id":"get-user--\"indorrect-user-id\"","type":"scenario","keyword":"Scenario Outline","steps":[{"name":"params { id: \"*5q\/\" }","result":{"duration":376900,"status":"passed"},"match":{"location":"karate","arguments":[]},"keyword":"Given","line":75},{"name":"path 'user'","result":{"duration":496300,"status":"passed"},"match":{"location":"karate","arguments":[]},"keyword":"Given","line":76},{"name":"method get","result":{"duration":8495600,"status":"passed"},"match":{"location":"karate","arguments":[]},"keyword":"When","line":77,"doc_string":{"content_type":"","value":"00:31:43.417 request:\n1 > GET http:\/\/127.0.0.1:8900\/user?id=*5q%2F\n1 > Host: 127.0.0.1:8900\n1 > Connection: Keep-Alive\n1 > User-Agent: Apache-HttpClient\/4.5.13 (Java\/1.8.0_301)\n1 > Accept-Encoding: gzip,deflate\n\n\n00:31:43.423 response time in milliseconds: 6\n1 < 404\n1 < Content-Type: text\/plain;charset=UTF-8\n1 < Content-Length: 14\n1 < Date: Mon, 20 Sep 2021 22:31:43 GMT\nUser not found\n","line":77}},{"name":"status 404","result":{"duration":6100,"status":"passed"},"match":{"location":"karate","arguments":[]},"keyword":"Then","line":78},{"name":"match response == \"User not found\"","result":{"duration":720500,"status":"passed"},"match":{"location":"karate","arguments":[]},"keyword":"And","line":79}],"tags":[{"name":"@GetUserNegative","line":73}]},{"line":3,"name":"","description":"","type":"background","keyword":"Background","steps":[{"name":"def dataGenerator = Java.type('helpers.DataGenerator')","result":{"duration":429300,"status":"passed"},"match":{"location":"karate","arguments":[]},"keyword":"*","line":4,"doc_string":{"content_type":"","value":"00:31:43.422 karate.env system property was: null \n","line":4}},{"name":"url apiURL","result":{"duration":66300,"status":"passed"},"match":{"location":"karate","arguments":[]},"keyword":"Given","line":5}]},{"line":84,"name":"Get User: \"No user id\"","description":"","id":"get-user--\"no-user-id\"","type":"scenario","keyword":"Scenario Outline","steps":[{"name":"params { id: null }","result":{"duration":115500,"status":"passed"},"match":{"location":"karate","arguments":[]},"keyword":"Given","line":75},{"name":"path 'user'","result":{"duration":720900,"status":"passed"},"match":{"location":"karate","arguments":[]},"keyword":"Given","line":76},{"name":"method get","result":{"duration":6008100,"status":"passed"},"match":{"location":"karate","arguments":[]},"keyword":"When","line":77,"doc_string":{"content_type":"","value":"00:31:43.426 request:\n1 > GET http:\/\/127.0.0.1:8900\/user\n1 > Host: 127.0.0.1:8900\n1 > Connection: Keep-Alive\n1 > User-Agent: Apache-HttpClient\/4.5.13 (Java\/1.8.0_301)\n1 > Accept-Encoding: gzip,deflate\n\n\n00:31:43.430 response time in milliseconds: 4\n1 < 500\n1 < Content-Type: text\/plain;charset=UTF-8\n1 < Content-Length: 11\n1 < Date: Mon, 20 Sep 2021 22:31:43 GMT\n1 < Connection: close\nID erroneus\n","line":77}},{"name":"status 500","result":{"duration":2700,"status":"passed"},"match":{"location":"karate","arguments":[]},"keyword":"Then","line":78},{"name":"match response == \"ID erroneus\"","result":{"duration":451100,"status":"passed"},"match":{"location":"karate","arguments":[]},"keyword":"And","line":79}],"tags":[{"name":"@GetUserNegative","line":73}]},{"line":3,"name":"","description":"","type":"background","keyword":"Background","steps":[{"name":"def dataGenerator = Java.type('helpers.DataGenerator')","result":{"duration":232000,"status":"passed"},"match":{"location":"karate","arguments":[]},"keyword":"*","line":4,"doc_string":{"content_type":"","value":"00:31:43.421 karate.env system property was: null \n","line":4}},{"name":"url apiURL","result":{"duration":41600,"status":"passed"},"match":{"location":"karate","arguments":[]},"keyword":"Given","line":5}]},{"line":97,"name":"Post user: \"No email\"","description":"","id":"post-user--\"no-email\"","type":"scenario","keyword":"Scenario Outline","steps":[{"name":"path 'user'","result":{"duration":49000,"status":"passed"},"match":{"location":"karate","arguments":[]},"keyword":"Given","line":89},{"name":"request {email:\"\", name:\"Karl\"}","result":{"duration":116800,"status":"passed"},"match":{"location":"karate","arguments":[]},"keyword":"And","line":90},{"name":"method Post","result":{"duration":4562200,"status":"passed"},"match":{"location":"karate","arguments":[]},"keyword":"When","line":91,"doc_string":{"content_type":"","value":"00:31:43.423 request:\n1 > POST http:\/\/127.0.0.1:8900\/user\n1 > Content-Type: application\/json; charset=UTF-8\n1 > Content-Length: 26\n1 > Host: 127.0.0.1:8900\n1 > Connection: Keep-Alive\n1 > User-Agent: Apache-HttpClient\/4.5.13 (Java\/1.8.0_301)\n1 > Accept-Encoding: gzip,deflate\n{\"email\":\"\",\"name\":\"Karl\"}\n\n00:31:43.426 response time in milliseconds: 3\n1 < 409\n1 < Content-Type: text\/plain;charset=UTF-8\n1 < Content-Length: 12\n1 < Date: Mon, 20 Sep 2021 22:31:43 GMT\nCheck fields\n","line":91}},{"name":"status 409","result":{"duration":4600,"status":"passed"},"match":{"location":"karate","arguments":[]},"keyword":"Then","line":92},{"name":"match response == \"Check fields\"","result":{"duration":482500,"status":"passed"},"match":{"location":"karate","arguments":[]},"keyword":"And","line":93}],"tags":[{"name":"@CreateUserNegative","line":87}]},{"line":3,"name":"","description":"","type":"background","keyword":"Background","steps":[{"name":"def dataGenerator = Java.type('helpers.DataGenerator')","result":{"duration":170800,"status":"passed"},"match":{"location":"karate","arguments":[]},"keyword":"*","line":4,"doc_string":{"content_type":"","value":"00:31:43.427 karate.env system property was: null \n","line":4}},{"name":"url apiURL","result":{"duration":135200,"status":"passed"},"match":{"location":"karate","arguments":[]},"keyword":"Given","line":5}]},{"line":98,"name":"Post user: \"No name\"","description":"","id":"post-user--\"no-name\"","type":"scenario","keyword":"Scenario Outline","steps":[{"name":"path 'user'","result":{"duration":86800,"status":"passed"},"match":{"location":"karate","arguments":[]},"keyword":"Given","line":89},{"name":"request {email:\"my@email.com\", name:\"\"}","result":{"duration":151300,"status":"passed"},"match":{"location":"karate","arguments":[]},"keyword":"And","line":90},{"name":"method Post","result":{"duration":10926600,"status":"passed"},"match":{"location":"karate","arguments":[]},"keyword":"When","line":91,"doc_string":{"content_type":"","value":"00:31:43.434 request:\n1 > POST http:\/\/127.0.0.1:8900\/user\n1 > Content-Type: application\/json; charset=UTF-8\n1 > Content-Length: 34\n1 > Host: 127.0.0.1:8900\n1 > Connection: Keep-Alive\n1 > User-Agent: Apache-HttpClient\/4.5.13 (Java\/1.8.0_301)\n1 > Accept-Encoding: gzip,deflate\n{\"email\":\"my@email.com\",\"name\":\"\"}\n\n00:31:43.439 response time in milliseconds: 4\n1 < 409\n1 < Content-Type: text\/plain;charset=UTF-8\n1 < Content-Length: 12\n1 < Date: Mon, 20 Sep 2021 22:31:43 GMT\nCheck fields\n","line":91}},{"name":"status 409","result":{"duration":4500,"status":"passed"},"match":{"location":"karate","arguments":[]},"keyword":"Then","line":92},{"name":"match response == \"Check fields\"","result":{"duration":585300,"status":"passed"},"match":{"location":"karate","arguments":[]},"keyword":"And","line":93}],"tags":[{"name":"@CreateUserNegative","line":87}]},{"line":3,"name":"","description":"","type":"background","keyword":"Background","steps":[{"name":"def dataGenerator = Java.type('helpers.DataGenerator')","result":{"duration":189300,"status":"passed"},"match":{"location":"karate","arguments":[]},"keyword":"*","line":4,"doc_string":{"content_type":"","value":"00:31:43.429 karate.env system property was: null \n","line":4}},{"name":"url apiURL","result":{"duration":33000,"status":"passed"},"match":{"location":"karate","arguments":[]},"keyword":"Given","line":5}]},{"line":99,"name":"Post user: \"No email or name\"","description":"","id":"post-user--\"no-email-or-name\"","type":"scenario","keyword":"Scenario Outline","steps":[{"name":"path 'user'","result":{"duration":42100,"status":"passed"},"match":{"location":"karate","arguments":[]},"keyword":"Given","line":89},{"name":"request {email:\"\", name:\"\"}","result":{"duration":86500,"status":"passed"},"match":{"location":"karate","arguments":[]},"keyword":"And","line":90},{"name":"method Post","result":{"duration":7079900,"status":"passed"},"match":{"location":"karate","arguments":[]},"keyword":"When","line":91,"doc_string":{"content_type":"","value":"00:31:43.431 request:\n1 > POST http:\/\/127.0.0.1:8900\/user\n1 > Content-Type: application\/json; charset=UTF-8\n1 > Content-Length: 22\n1 > Host: 127.0.0.1:8900\n1 > Connection: Keep-Alive\n1 > User-Agent: Apache-HttpClient\/4.5.13 (Java\/1.8.0_301)\n1 > Accept-Encoding: gzip,deflate\n{\"email\":\"\",\"name\":\"\"}\n\n00:31:43.437 response time in milliseconds: 6\n1 < 409\n1 < Content-Type: text\/plain;charset=UTF-8\n1 < Content-Length: 12\n1 < Date: Mon, 20 Sep 2021 22:31:43 GMT\nCheck fields\n","line":91}},{"name":"status 409","result":{"duration":4600,"status":"passed"},"match":{"location":"karate","arguments":[]},"keyword":"Then","line":92},{"name":"match response == \"Check fields\"","result":{"duration":252600,"status":"passed"},"match":{"location":"karate","arguments":[]},"keyword":"And","line":93}],"tags":[{"name":"@CreateUserNegative","line":87}]},{"line":3,"name":"","description":"","type":"background","keyword":"Background","steps":[{"name":"def dataGenerator = Java.type('helpers.DataGenerator')","result":{"duration":223700,"status":"passed"},"match":{"location":"karate","arguments":[]},"keyword":"*","line":4,"doc_string":{"content_type":"","value":"00:31:43.435 karate.env system property was: null \n","line":4}},{"name":"url apiURL","result":{"duration":46800,"status":"passed"},"match":{"location":"karate","arguments":[]},"keyword":"Given","line":5}]},{"line":100,"name":"Post user: \"Malformed email\"","description":"","id":"post-user--\"malformed-email\"","type":"scenario","keyword":"Scenario Outline","steps":[{"name":"path 'user'","result":{"duration":39400,"status":"passed"},"match":{"location":"karate","arguments":[]},"keyword":"Given","line":89},{"name":"request {email:\"my.email.com\", name:\"Karl\"}","result":{"duration":99100,"status":"passed"},"match":{"location":"karate","arguments":[]},"keyword":"And","line":90},{"name":"method Post","result":{"duration":11741000,"status":"passed"},"match":{"location":"karate","arguments":[]},"keyword":"When","line":91,"doc_string":{"content_type":"","value":"00:31:43.437 request:\n1 > POST http:\/\/127.0.0.1:8900\/user\n1 > Content-Type: application\/json; charset=UTF-8\n1 > Content-Length: 38\n1 > Host: 127.0.0.1:8900\n1 > Connection: Keep-Alive\n1 > User-Agent: Apache-HttpClient\/4.5.13 (Java\/1.8.0_301)\n1 > Accept-Encoding: gzip,deflate\n{\"email\":\"my.email.com\",\"name\":\"Karl\"}\n\n00:31:43.448 response time in milliseconds: 10\n1 < 500\n1 < Content-Type: application\/json;charset=UTF-8\n1 < Transfer-Encoding: chunked\n1 < Date: Mon, 20 Sep 2021 22:31:43 GMT\n1 < Connection: close\n{\"timestamp\":\"2021-09-20T22:31:43.446+0000\",\"status\":500,\"error\":\"Internal Server Error\",\"message\":\"malformed email\",\"path\":\"\/user\"}\n","line":91}},{"name":"status 500","result":{"duration":3800,"status":"passed"},"match":{"location":"karate","arguments":[]},"keyword":"Then","line":92},{"name":"match response == {\"timestamp\":\"#string\",\"status\":500,\"error\":\"Internal Server Error\",\"message\":\"malformed email\",\"path\":\"\/user\"}","result":{"duration":329800,"status":"passed"},"match":{"location":"karate","arguments":[]},"keyword":"And","line":93}],"tags":[{"name":"@CreateUserNegative","line":87}]},{"line":3,"name":"","description":"","type":"background","keyword":"Background","steps":[{"name":"def dataGenerator = Java.type('helpers.DataGenerator')","result":{"duration":174900,"status":"passed"},"match":{"location":"karate","arguments":[]},"keyword":"*","line":4,"doc_string":{"content_type":"","value":"00:31:43.440 karate.env system property was: null \n","line":4}},{"name":"url apiURL","result":{"duration":30800,"status":"passed"},"match":{"location":"karate","arguments":[]},"keyword":"Given","line":5}]},{"line":101,"name":"Post user: \"No request parameter\"","description":"","id":"post-user--\"no-request-parameter\"","type":"scenario","keyword":"Scenario Outline","steps":[{"name":"path 'user'","result":{"duration":37400,"status":"passed"},"match":{"location":"karate","arguments":[]},"keyword":"Given","line":89},{"name":"request null","result":{"duration":3502300,"status":"passed"},"match":{"location":"karate","arguments":[]},"keyword":"And","line":90},{"name":"method Post","result":{"duration":7286100,"status":"passed"},"match":{"location":"karate","arguments":[]},"keyword":"When","line":91,"doc_string":{"content_type":"","value":"00:31:43.445 request:\n1 > POST http:\/\/127.0.0.1:8900\/user\n1 > Host: 127.0.0.1:8900\n1 > Connection: Keep-Alive\n1 > User-Agent: Apache-HttpClient\/4.5.13 (Java\/1.8.0_301)\n1 > Accept-Encoding: gzip,deflate\n\n\n00:31:43.451 response time in milliseconds: 6\n1 < 400\n1 < Content-Type: application\/json;charset=UTF-8\n1 < Transfer-Encoding: chunked\n1 < Date: Mon, 20 Sep 2021 22:31:43 GMT\n1 < Connection: close\n{\"timestamp\":\"2021-09-20T22:31:43.450+0000\",\"status\":400,\"error\":\"Bad Request\",\"message\":\"Required request body is missing: public restservice.entity.User restservice.controller.UserController.createUser(restservice.api.UserRequest) throws java.lang.Exception\",\"path\":\"\/user\"}\n","line":91}},{"name":"status 400","result":{"duration":4500,"status":"passed"},"match":{"location":"karate","arguments":[]},"keyword":"Then","line":92},{"name":"match response == {\"timestamp\":\"#string\",\"status\":400,\"error\":\"Bad Request\",\"message\":\"#string\",\"path\":\"\/user\"}","result":{"duration":295800,"status":"passed"},"match":{"location":"karate","arguments":[]},"keyword":"And","line":93}],"tags":[{"name":"@CreateUserNegative","line":87}]}],"name":"examples\/users\/users.feature","description":"Tests for User Controller","id":"tests-for-user-controller","keyword":"Feature","uri":"examples\/users\/users.feature"}]